{
  "history": [
    {
      "timestamp": "2026-05-01T17:00:00.000Z",
      "statuses": {
        "code.functor.systems": "online",
        "functor.mit.edu": "online",
        "slop.kaitotlex.engineering": "online",
        "yap.kaitotlex.systems": "online",
        "matrix.functor.systems": "online",
        "missioncontrol.kaitotlex.systems": "online"
      }
    },
    {
      "timestamp": "2026-05-01T18:00:00.000Z",
      "statuses": {
        "functor.mit.edu": "online",
        "yap.kaitotlex.systems": "online",
        "matrix.functor.systems": "online",
        "code.functor.systems": "online",
        "slop.kaitotlex.engineering": "online",
        "missioncontrol.kaitotlex.systems": "online"
      }
    },
    {
      "timestamp": "2026-05-01T19:00:00.000Z",
      "statuses": {
        "yap.kaitotlex.systems": "online",
        "code.functor.systems": "online",
        "slop.kaitotlex.engineering": "online",
        "functor.mit.edu": "online",
        "matrix.functor.systems": "online",
        "missioncontrol.kaitotlex.systems": "online"
      }
    },
    {
      "timestamp": "2026-05-01T20:00:00.000Z",
      "statuses": {
        "code.functor.systems": "online",
        "slop.kaitotlex.engineering": "online",
        "yap.kaitotlex.systems": "online",
        "functor.mit.edu": "online",
        "matrix.functor.systems": "online",
        "missioncontrol.kaitotlex.systems": "online"
      }
    },
    {
      "timestamp": "2026-05-01T21:00:00.000Z",
      "statuses": {
        "functor.mit.edu": "online",
        "matrix.functor.systems": "online",
        "slop.kaitotlex.engineering": "online",
        "yap.kaitotlex.systems": "online",
        "code.functor.systems": "online",
        "missioncontrol.kaitotlex.systems": "online"
      }
    },
    {
      "timestamp": "2026-05-01T22:00:00.000Z",
      "statuses": {
        "code.functor.systems": "online",
        "yap.kaitotlex.systems": "online",
        "functor.mit.edu": "online",
        "matrix.functor.systems": "online",
        "slop.kaitotlex.engineering": "online",
        "missioncontrol.kaitotlex.systems": "online"
      }
    },
    {
      "timestamp": "2026-05-01T23:00:00.000Z",
      "statuses": {
        "code.functor.systems": "online",
        "functor.mit.edu": "online",
        "matrix.functor.systems": "online",
        "yap.kaitotlex.systems": "online",
        "missioncontrol.kaitotlex.systems": "online",
        "slop.kaitotlex.engineering": "online"
      }
    },
    {
      "timestamp": "2026-05-02T00:00:00.000Z",
      "statuses": {
        "functor.mit.edu": "online",
        "matrix.functor.systems": "online",
        "yap.kaitotlex.systems": "online",
        "slop.kaitotlex.engineering": "online",
        "missioncontrol.kaitotlex.systems": "online",
        "code.functor.systems": "online"
      }
    },
    {
      "timestamp": "2026-05-02T01:00:00.000Z",
      "statuses": {
        "functor.mit.edu": "online",
        "matrix.functor.systems": "online",
        "code.functor.systems": "online",
        "slop.kaitotlex.engineering": "online",
        "yap.kaitotlex.systems": "online",
        "missioncontrol.kaitotlex.systems": "online"
      }
    },
    {
      "timestamp": "2026-05-02T03:00:00.000Z",
      "statuses": {
        "code.functor.systems": "online",
        "slop.kaitotlex.engineering": "online",
        "yap.kaitotlex.systems": "online",
        "missioncontrol.kaitotlex.systems": "online",
        "functor.mit.edu": "online",
        "matrix.functor.systems": "online"
      }
    },
    {
      "timestamp": "2026-05-02T04:00:00.000Z",
      "statuses": {
        "code.functor.systems": "online",
        "slop.kaitotlex.engineering": "online",
        "functor.mit.edu": "online",
        "matrix.functor.systems": "online",
        "yap.kaitotlex.systems": "online",
        "missioncontrol.kaitotlex.systems": "online"
      }
    },
    {
      "timestamp": "2026-05-02T05:00:00.000Z",
      "statuses": {
        "functor.mit.edu": "online",
        "matrix.functor.systems": "online",
        "yap.kaitotlex.systems": "online",
        "code.functor.systems": "online",
        "slop.kaitotlex.engineering": "online",
        "missioncontrol.kaitotlex.systems": "online"
      }
    }
  ]
}
