{
  "history": [
    {
      "timestamp": "2026-05-31T00:00:00.000Z",
      "statuses": {
        "slop.kaitotlex.engineering": "offline",
        "yap.kaitotlex.systems": "online",
        "code.functor.systems": "online",
        "missioncontrol.kaitotlex.systems": "online",
        "matrix.functor.systems": "online",
        "functor.mit.edu": "offline"
      }
    },
    {
      "timestamp": "2026-05-31T01:00:00.000Z",
      "statuses": {
        "slop.kaitotlex.engineering": "offline",
        "code.functor.systems": "online",
        "yap.kaitotlex.systems": "online",
        "matrix.functor.systems": "online",
        "missioncontrol.kaitotlex.systems": "online",
        "functor.mit.edu": "offline"
      }
    },
    {
      "timestamp": "2026-05-31T03:00:00.000Z",
      "statuses": {
        "slop.kaitotlex.engineering": "offline",
        "matrix.functor.systems": "online",
        "yap.kaitotlex.systems": "online",
        "code.functor.systems": "online",
        "missioncontrol.kaitotlex.systems": "online",
        "functor.mit.edu": "offline"
      }
    },
    {
      "timestamp": "2026-05-31T05:00:00.000Z",
      "statuses": {
        "code.functor.systems": "online",
        "slop.kaitotlex.engineering": "offline",
        "missioncontrol.kaitotlex.systems": "online",
        "yap.kaitotlex.systems": "online",
        "matrix.functor.systems": "online",
        "functor.mit.edu": "offline"
      }
    },
    {
      "timestamp": "2026-05-31T07:00:00.000Z",
      "statuses": {
        "code.functor.systems": "online",
        "yap.kaitotlex.systems": "online",
        "slop.kaitotlex.engineering": "offline",
        "missioncontrol.kaitotlex.systems": "online",
        "matrix.functor.systems": "online",
        "functor.mit.edu": "offline"
      }
    },
    {
      "timestamp": "2026-05-31T08:00:00.000Z",
      "statuses": {
        "code.functor.systems": "online",
        "slop.kaitotlex.engineering": "offline",
        "yap.kaitotlex.systems": "online",
        "matrix.functor.systems": "online",
        "missioncontrol.kaitotlex.systems": "online",
        "functor.mit.edu": "offline"
      }
    },
    {
      "timestamp": "2026-05-31T09:00:00.000Z",
      "statuses": {
        "slop.kaitotlex.engineering": "offline",
        "matrix.functor.systems": "online",
        "yap.kaitotlex.systems": "online",
        "code.functor.systems": "online",
        "missioncontrol.kaitotlex.systems": "online",
        "functor.mit.edu": "offline"
      }
    },
    {
      "timestamp": "2026-05-31T10:00:00.000Z",
      "statuses": {
        "slop.kaitotlex.engineering": "offline",
        "matrix.functor.systems": "online",
        "code.functor.systems": "online",
        "missioncontrol.kaitotlex.systems": "online",
        "yap.kaitotlex.systems": "online",
        "functor.mit.edu": "offline"
      }
    },
    {
      "timestamp": "2026-05-31T11:00:00.000Z",
      "statuses": {
        "slop.kaitotlex.engineering": "offline",
        "code.functor.systems": "online",
        "yap.kaitotlex.systems": "online",
        "matrix.functor.systems": "online",
        "missioncontrol.kaitotlex.systems": "online",
        "functor.mit.edu": "offline"
      }
    },
    {
      "timestamp": "2026-05-31T12:00:00.000Z",
      "statuses": {
        "slop.kaitotlex.engineering": "offline",
        "yap.kaitotlex.systems": "online",
        "matrix.functor.systems": "online",
        "code.functor.systems": "online",
        "missioncontrol.kaitotlex.systems": "online",
        "functor.mit.edu": "offline"
      }
    },
    {
      "timestamp": "2026-05-31T13:00:00.000Z",
      "statuses": {
        "slop.kaitotlex.engineering": "offline",
        "code.functor.systems": "online",
        "matrix.functor.systems": "online",
        "yap.kaitotlex.systems": "online",
        "missioncontrol.kaitotlex.systems": "online",
        "functor.mit.edu": "offline"
      }
    },
    {
      "timestamp": "2026-05-31T14:00:00.000Z",
      "statuses": {
        "yap.kaitotlex.systems": "online",
        "code.functor.systems": "online",
        "slop.kaitotlex.engineering": "offline",
        "matrix.functor.systems": "online",
        "missioncontrol.kaitotlex.systems": "online",
        "functor.mit.edu": "offline"
      }
    }
  ]
}
